biognosis/.DS_Store
biognosis/version.py
biognosis/__init__.py
biognosis/api.py
biognosis/cli.py
biognosis/py.typed
biognosis/sources/biogrid.py
biognosis/sources/constants.py
biognosis/sources/agr.py
biognosis/sources/__init__.py
biognosis/sources/goa.py
biognosis/sources/excape.py
biognosis/__main__.py
biognosis-0.0.2.dist-info/licenses/LICENSE
biognosis-0.0.2.dist-info/WHEEL
biognosis-0.0.2.dist-info/entry_points.txt
biognosis-0.0.2.dist-info/METADATA
biognosis-0.0.2.dist-info/RECORD
